pyergast/__init__.py
pyergast/pyergast.py
pyergast-0.1.0.dist-info/LICENSE
pyergast-0.1.0.dist-info/WHEEL
pyergast-0.1.0.dist-info/METADATA
pyergast-0.1.0.dist-info/RECORD
