Metadata-Version: 2.1
Name: pyergast
Version: 0.1.0
Summary: Python pandas wrapper for the Ergast F1 API
Home-page: https://github.com/weiranyu/pyErgast
Author: Weiran Yu
Author-email: weiranyu@hotmail.com
Requires-Python: >=3.7,<4.0
Classifier: Programming Language :: Python :: 3
Classifier: Programming Language :: Python :: 3.7
Classifier: Programming Language :: Python :: 3.8
Requires-Dist: pandas (>=1.1.5,<2.0.0)
Requires-Dist: requests (>=2.25.0,<3.0.0)
Project-URL: Documentation, https://pyergast.readthedocs.io/en/latest/
Project-URL: Repository, https://github.com/weiranyu/pyErgast
